Metadata-Version: 2.1
Name: ipyTransferFunction
Version: 0.2.0
Summary: Transfer function editor for Blue Brain BioExplorer
Home-page: https://github.com/favreau/ipyTransferFunction.git
Author: Cyrille Favreau
Author-email: cyrille.favreau@epfl.ch
License: GNU LGPL
Keywords: covid,covid19,coronavirus,bbp,blue,brain,virus,molecule,molecular system
Platform: UNKNOWN
Classifier: Development Status :: 4 - Beta
Classifier: License :: OSI Approved :: GNU Lesser General Public License v3 (LGPLv3)
Classifier: Operating System :: OS Independent
Classifier: Programming Language :: Python :: 3.6
Classifier: Programming Language :: Python :: 3.7
Classifier: Programming Language :: Python :: 3.8
Classifier: Topic :: Software Development :: Libraries
Classifier: Topic :: Software Development :: Libraries :: Python Modules
